openhltest/__init__.py
openhltest/httptransport.py
openhltest/openhltest.py
openhltest/yangbase.py
openhltest/docs/openhltest.html
openhltest/docs/openhltest.md
openhltest/docs/openhltest_model.html
openhltest/docs/openhltest_model.txt
openhltest/samples/vendor_prototype_demo.py
openhltest-0.1a111.dist-info/DESCRIPTION.rst
openhltest-0.1a111.dist-info/METADATA
openhltest-0.1a111.dist-info/RECORD
openhltest-0.1a111.dist-info/WHEEL
openhltest-0.1a111.dist-info/metadata.json
openhltest-0.1a111.dist-info/top_level.txt
