Metadata-Version: 2.0
Name: openhltest
Version: 0.1a111
Summary: OpenHLTest Python Client
Home-page: https://github.com/openhltest/data-models
Author: andrey.balogh@gmail.com
Author-email: andrey.balogh@gmail.com
License: MIT
Keywords: openhltest test tool ixia spirent restconf automation
Platform: UNKNOWN
Classifier: Development Status :: 3 - Alpha
Classifier: Intended Audience :: Developers
Classifier: Topic :: Software Development
Classifier: License :: OSI Approved :: MIT License
Classifier: Programming Language :: Python :: 2.7
Classifier: Programming Language :: Python :: 3
Requires-Python: >=2.7, <4
Requires-Dist: requests
